[
  {
    "ContainingType": "Hotel.Controllers.RoomsController",
    "Method": "Test",
    "RelativePath": "api/Rooms",
    "HttpMethod": "GET",
    "IsController": true,
    "Order": 0,
    "Parameters": [],
    "ReturnTypes": [
      {
        "Type": "System.String",
        "MediaTypes": [
          "text/plain",
          "application/json",
          "text/json"
        ],
        "StatusCode": 200
      }
    ]
  },
  {
    "ContainingType": "Hotel.Controllers.RoomsController",
    "Method": "Save",
    "RelativePath": "api/Rooms",
    "HttpMethod": "POST",
    "IsController": true,
    "Order": 0,
    "Parameters": [
      {
        "Name": "room",
        "Type": "Hotel.Models.Room",
        "IsRequired": true
      }
    ],
    "ReturnTypes": [
      {
        "Type": "Hotel.Models.Room",
        "MediaTypes": [
          "text/plain",
          "application/json",
          "text/json"
        ],
        "StatusCode": 200
      }
    ]
  }
]